tocy.py
tocy-0.13.dist-info/LICENSE
tocy-0.13.dist-info/METADATA
tocy-0.13.dist-info/WHEEL
tocy-0.13.dist-info/top_level.txt
tocy-0.13.dist-info/RECORD
