Metadata-Version: 2.1
Name: tocy
Version: 0.13
Summary: To generate Table of Content (TOC) for markdown file (like README.md) automatically
Author-email: xinlin-z <xinlin.zhang@hotmail.com>
Project-URL: homepage, https://github.com/xinlin-z/tocy
Classifier: Programming Language :: Python :: 3
Classifier: License :: OSI Approved :: MIT License
Classifier: Operating System :: OS Independent
Requires-Python: >=3.8
License-File: LICENSE
